AUTHORS.rst
CONTRIBUTING.rst
HISTORY.rst
LICENSE
MANIFEST.in
README.rst
setup.py
bootstrap3/__init__.py
bootstrap3/bootstrap.py
bootstrap3/components.py
bootstrap3/exceptions.py
bootstrap3/forms.py
bootstrap3/legacy.py
bootstrap3/models.py
bootstrap3/renderers.py
bootstrap3/tests.py
bootstrap3/text.py
bootstrap3/utils.py
bootstrap3/static/bootstrap3/css/infiniboot.css
bootstrap3/static/bootstrap3/css/infinidat.css
bootstrap3/static/bootstrap3/css/opensans.css
bootstrap3/static/bootstrap3/fonts/OpenSans-Bold.eot
bootstrap3/static/bootstrap3/fonts/OpenSans-Bold.ttf
bootstrap3/static/bootstrap3/fonts/OpenSans-Bold.woff
bootstrap3/static/bootstrap3/fonts/OpenSans-Light.eot
bootstrap3/static/bootstrap3/fonts/OpenSans-Light.ttf
bootstrap3/static/bootstrap3/fonts/OpenSans-Light.woff
bootstrap3/static/bootstrap3/fonts/OpenSans-Regular.eot
bootstrap3/static/bootstrap3/fonts/OpenSans-Regular.ttf
bootstrap3/static/bootstrap3/fonts/OpenSans-Regular.woff
bootstrap3/static/bootstrap3/fonts/OpenSans-Semibold.eot
bootstrap3/static/bootstrap3/fonts/OpenSans-Semibold.ttf
bootstrap3/static/bootstrap3/fonts/OpenSans-Semibold.woff
bootstrap3/templates/bootstrap3/bootstrap3.html
bootstrap3/templates/bootstrap3/field_help_text_and_errors.html
bootstrap3/templates/bootstrap3/form_errors.html
bootstrap3/templates/bootstrap3/messages.html
bootstrap3/templates/bootstrap3/pagination.html
bootstrap3/templatetags/__init__.py
bootstrap3/templatetags/bootstrap3.py
demo/manage.py
demo/demo/__init__.py
demo/demo/forms.py
demo/demo/settings.py
demo/demo/urls.py
demo/demo/views.py
demo/demo/wsgi.py
demo/demo/templates/demo/base.html
demo/demo/templates/demo/bootstrap.html
demo/demo/templates/demo/form.html
demo/demo/templates/demo/form_by_field.html
demo/demo/templates/demo/form_horizontal.html
demo/demo/templates/demo/form_inline.html
demo/demo/templates/demo/form_with_files.html
demo/demo/templates/demo/formset.html
demo/demo/templates/demo/home.html
demo/demo/templates/demo/misc.html
infinidat_django_bootstrap3.egg-info/PKG-INFO
infinidat_django_bootstrap3.egg-info/SOURCES.txt
infinidat_django_bootstrap3.egg-info/dependency_links.txt
infinidat_django_bootstrap3.egg-info/not-zip-safe
infinidat_django_bootstrap3.egg-info/top_level.txt